{
	"id": "custom-dice-d6",
	"title": "Custom Dice Template",
	"description": "",
  
	"version": "0.1.0",
  
  "compatibility": {
    "minimum": "10",
    "verified": "10",
    "maximum": "10"
  },
  
  "authors": [
    {
      "name": "Mestre Digital",
      "url": "https://www.youtube.com/c/MestreDigital",
      "flags": {}
    }
  ],
  
	"esmodules": [
		"./scripts/main.js"
	],
	"styles": [
		"./css/style.css"
	],
	"url": "https://github.com/brunocalado/custom-dice-d6",
	"manifest": "",
	"download": "",

  "relationships": {
    "requires": [
      {
        "id": "dice-so-nice",
        "type": "module",
        "manifest": "https://gitlab.com/riccisi/foundryvtt-dice-so-nice/-/raw/master/module/module.json"
      }
    ]
  }
}

